koTextAug/__init__.py
koTextAug/textAugmentation.py
koTextAug/tokenizer.py
koTextAug/utils.py
koTextAug-1.0.0.7.dist-info/METADATA
koTextAug-1.0.0.7.dist-info/WHEEL
koTextAug-1.0.0.7.dist-info/top_level.txt
koTextAug-1.0.0.7.dist-info/RECORD
