Metadata-Version: 2.1
Name: koTextAug
Version: 1.0.0.7
Summary: Korean Text data Augmentation package
Home-page: https://ssu-humane.github.io/
Author: Humane Lab
Author-email: parkchaewon8566@gmail.com
License: MIT
Platform: UNKNOWN
Requires-Python: >=3
